twat_image/__init__.py
twat_image/__version__.py
twat_image/gray2alpha.py
twat_image-2.7.5.dist-info/METADATA
twat_image-2.7.5.dist-info/WHEEL
twat_image-2.7.5.dist-info/entry_points.txt
twat_image-2.7.5.dist-info/licenses/LICENSE
twat_image-2.7.5.dist-info/RECORD
